envkp/__init__.py
envkp/core.py
envkp-0.7.0.dist-info/licenses/LICENSE
envkp-0.7.0.dist-info/METADATA
envkp-0.7.0.dist-info/WHEEL
envkp-0.7.0.dist-info/entry_points.txt
envkp-0.7.0.dist-info/top_level.txt
envkp-0.7.0.dist-info/RECORD
