Metadata-Version: 2.4
Name: envkp
Version: 0.7.0
Summary: GitHub Environment Housekeeper
Author-email: hwakabh <hrykwkbys1024@gmail.com>
License: MIT License
Project-URL: Homepage, https://github.com/hwakabh/envkeeper
Project-URL: Bug Tracker, https://github.com/hwakabh/envkeeper/issues
Project-URL: Source, https://github.com/hwakabh/envkeeper
Classifier: Development Status :: 3 - Alpha
Classifier: Intended Audience :: Developers
Classifier: License :: OSI Approved :: MIT License
Classifier: Programming Language :: Python :: 3.12
License-File: LICENSE
Requires-Dist: setuptools
Provides-Extra: dev
Dynamic: license-file
